data_prc/__init__.py
data_prc/caracteristics.py
data_prc/core.py
data_prc/departements.py
data_prc/lieux.py
data_prc/usagers.py
data_prc/vehicules.py
rw_data_proc/__init__.py
rw_data_proc/caracteristics.py
rw_data_proc/core.py
rw_data_proc/departements.py
rw_data_proc/lieux.py
rw_data_proc/usagers.py
rw_data_proc/vehicules.py
roadwatch_data_processor-0.2.7.dist-info/LICENSE
roadwatch_data_processor-0.2.7.dist-info/METADATA
roadwatch_data_processor-0.2.7.dist-info/WHEEL
roadwatch_data_processor-0.2.7.dist-info/top_level.txt
roadwatch_data_processor-0.2.7.dist-info/RECORD
