Metadata-Version: 2.1
Name: roadwatch-data-processor
Version: 0.2.7
Summary: A library for processing csv files on road accidents in France.                 Built for Project Roadwatch
Home-page: https://github.com/daniel-sasu/roadwatch-data-processor
Author: Daniel SASU
Author-email: daniel.sasu@mail.com
License: UNKNOWN
Platform: UNKNOWN
Classifier: Programming Language :: Python :: 3
Classifier: License :: OSI Approved :: MIT License
Classifier: Operating System :: OS Independent
Requires-Dist: pandas (==0.24.1)
Requires-Dist: numpy (==1.12.1)
